calculos_financeiros/__init__.py
calculos_financeiros/calc_juros.py
calculos_financeiros-0.0.1.dist-info/METADATA
calculos_financeiros-0.0.1.dist-info/WHEEL
calculos_financeiros-0.0.1.dist-info/top_level.txt
calculos_financeiros-0.0.1.dist-info/RECORD
