Metadata-Version: 2.1
Name: calculos_financeiros
Version: 0.0.1
Summary: Calculos de operações financeiras
Home-page: https://github.com
Author: Windlin
Requires-Python: >=3.8
